Metadata-Version: 2.1
Name: config-templater
Version: 0.1.1
Summary: Simple python module to generate configurations from templates
Home-page: https://github.com/squ4rks/config_templater
Author: Marcel Neidinger
Author-email: marcel.neidinger@nlogn.org
License: MIT license
Keywords: config_templater
Platform: UNKNOWN
Classifier: Development Status :: 2 - Pre-Alpha
Classifier: Intended Audience :: Developers
Classifier: License :: OSI Approved :: MIT License
Classifier: Natural Language :: English
Classifier: Programming Language :: Python :: 3
Classifier: Programming Language :: Python :: 3.5
Classifier: Programming Language :: Python :: 3.6
Classifier: Programming Language :: Python :: 3.7
Classifier: Programming Language :: Python :: 3.8
Requires-Python: >=3.5
